README.md
setup.py
tests/meta_data/__init__.py
ybconfig/__init__.py
ybconfig/singleton.py
ybconfig/version.py
ybconfig/web_config.py
ybconfig.egg-info/PKG-INFO
ybconfig.egg-info/SOURCES.txt
ybconfig.egg-info/dependency_links.txt
ybconfig.egg-info/entry_points.txt
ybconfig.egg-info/requires.txt
ybconfig.egg-info/top_level.txt