Metadata-Version: 2.1
Name: ybconfig
Version: 0.1.2
Summary: Basic configuration management for YB
Home-page: https://github.com/yellow-bird-consult/yb_config
Author: Maxwell Flitton
Author-email: maxwellflitton@gmail.com
License: UNKNOWN
Platform: UNKNOWN
